{
  "page_id": "596eb75dd9809a8d-artefacts-misc",
  "url": "https://www.achaea.com/game-help/?what=artefacts+misc",
  "what": "artefacts misc",
  "title": "Game Help | Achaea",
  "section_number": null,
  "discovered_from": "topic-guess:5bcd582f87d0c27d-artefact-pets",
  "command_candidates": [
    "HELP 7. 19 FOR THE COLOURS AVAILABLE. A SIGNET RING",
    "HELP ARTEFACT TRADEINS",
    "HELP ARTEFACT TRANSFERS",
    "HELP ARTEFACTS",
    "HELP ARTEFACTTATTOOS A PAIR OF IVORY DICE",
    "HELP CUSTOMISATION FOR MORE DETAILS",
    "HELP GAME HELP FILES FREQUENTLY ASKED QUESTIONS NEWBIE GUIDES HOW TO CONNECT EXTENSIONS SUPPORT CREDITS LOG IN ACHAEA HELP FILES ACHAEA HAS HUNDREDS OF HELP FILES TO YOU LEARN ABOUT ACHAEA. THIS IS A COPY OF THE IN-GAME HELP FILE STRUCTURE. HELP IN-GAME WILL SHOW YOU THIS SAME MENU. HELP",
    "HELP INDEX",
    "WHO CAN CHANGE THE PARTNER AT ANY TIME FOR A 150 CREDIT FEE. A MECHANICAL BOX"
  ],
  "topic_candidates": [
    "********************************************************************",
    "- generates",
    "- see",
    "-------------------",
    "18",
    "19",
    "19.10.6 miscellaneous artefacts",
    "7",
    ": 100 credits",
    ": 150 credits",
    ": 250 credits",
    ": 350 credits",
    ": 40 credits",
    ": 50 credits",
    ": 800 credits",
    "accept",
    "achaea",
    "achaea maps",
    "achaea wiki",
    "achaean",
    "aetolia",
    "agatheis",
    "artefact",
    "artefact tradeins",
    "artefact transfers",
    "artefacts",
    "artefacttattoos",
    "bound",
    "ceylon",
    "city-states",
    "classes",
    "community",
    "credits",
    "customisation",
    "customisation for more details",
    "death",
    "delos",
    "disabled",
    "enable all",
    "enabled",
    "extensions",
    "features overview",
    "files",
    "files to you learn about achaea. this is a copy of the in-game help file structu",
    "forums",
    "frequently asked questions",
    "game",
    "game help files",
    "game help | achaea",
    "game logs",
    "game messages",
    "game news",
    "help:",
    "history & mythos",
    "in-game will show you this same menu",
    "index",
    "iron realms entertainment",
    "iron realms entertainment!",
    "latest news",
    "log in",
    "lupus",
    "lusternia",
    "menu",
    "miscellaneous artefacts",
    "moghedu",
    "newbie guides",
    "note about stacking",
    "play!",
    "portal",
    "privacy overview",
    "privacy policy",
    "races",
    "ring",
    "save changes",
    "scroll to top",
    "strictly necessary cookies",
    "support",
    "syntax",
    "terms of service",
    "using the forums",
    "vault"
  ],
  "text": "Game Help | Achaea\nSkip to content\nPlay more great MUDs from\nIron Realms Entertainment!\nAetolia\nLusternia\nMenu\nPlay!\nGame\nFeatures Overview\nCity-States\nClasses\nRaces\nThe Gods of Achaea\nHistory & Mythos\nAchaea Maps\nPortal\nGame Messages\nGame News\nGame Logs\nCommunity\nForums\nUsing The Forums\nJoin us on Discord!\nAchaea Wiki\nLatest News\nHelp\nGame Help Files\nFrequently Asked Questions\nNewbie Guides\nHow to Connect\nExtensions\nSupport\nCredits\nLog In\nAchaea Help Files\nAchaea has hundreds of help files to you learn about Achaea. This is a copy of the in-game help file structure. HELP in-game will show you this same menu.\nHelp:\n[\nReturn to Help Index\n]\n19.10.6 Miscellaneous Artefacts\n(see also:\nHELP ARTEFACTS\n, HELP ARTEFACT TRANSFERS,\nHELP\nARTEFACT\nTRADEINS\n)\nArtefacts\nare special items that can be purchased only with\nBound\nCredits\n. Unless otherwise stated, artefacts can be purchased in Merentesh's series of\nshops\nin\nDelos\n. They will reset into your\ninventory\nfrequently, which means they cannot be loaned out, or stolen(!), for very long. Some only work for the owner. They never\ndecay\n. They cannot be changed to reset to anyone else's inventory, so do not\nbuy\nartefacts of any kind if you intend to\nsell\nthem.\nNote About Stacking\n-------------------\nArtefact effects (for similar artefacts) don't combine or stack. If you have,\nsay\n, a Collar of\nCeylon\nand a Collar of\nAgatheis\n, then only one will boost damage of a magical\nnature\n. If you have a Logosian\nRing\nand a Mayan Ring, then only one will increase the value of sipping a\nhealth\nelixir\n. In general, the best item rules, but there may be exceptions. So don't count on having two artefacts and somehow stacking their effects.\nProspero's Lesser\nVault\n:                                      350 Credits\nArtefact\npower\n:\nrift\n_expand\n- This vault will double the capacity of your rift. Exceptions may\napply\n!\n- Works when in inventory. Does not have to be\nwielded\n.\n- Will only work for owner.\n- Does not apply to liquids.\n- Only affects putting\nthings\nin. You can always take things out, even if you don't have your vault at the moment, and the actual contents of the rift are unchanged, whether you have your vault or not.\nProspero's Greater Vault:                                     500 Credits\nArtefact power: rift_expand\n- This vault will quadruple the capacity of your rift. Exceptions may apply!\n- See the Lesser Vault for more details.\nA Tippler's Tap:                                              300 Credits\nArtefact power: fluid_expansion\n- This vault will double the capacity of your liquid rift.\n- Works when in inventory. Does not have to be wielded.\n- Will only work for the owner.\nA Sot's Spigot:                                               400 Credits\nArtefact power: fluid_expansion\n- This vault will triple the capacity of your liquid rift.\n- Works when in inventory. Does not have to be wielded.\n- Will only work for the owner.\nA Phaestean Faucet:                                           500 Credits\nArtefact power: fluid_expansion\n- This vault will quadruple the capacity of your liquid rift.\n- Works when in inventory. Does not have to be wielded.\n- Will only work for the owner.\nA box of stasis:                                              750 Credits\n- This box will prevent the decay of items put inside it. Holds up to\n5\nitems. Certain items will still decay regardless.\nAn Eidolic ewer:                                              250 Credits\n- This ewer will serve as an extension of a\ncity\nfont\n.\n- TURN <ewer> <cityname> to set the ewer to a specific city.\n- TURN <ewer> to clear any city association for the ewer.\n-\nREAD\n<ewer> to check its current association, if any.\n- PUT <lesser eidolon> IN <ewer> to\nempower\nthe font.\nA gilded\npike\n:                                                150 Credits\n- When piking one head at a\ntime\nisn't enough.\n- Once planted, it will last for 5\nAchaean\nmonths\n, and will allow the owner to pike multiple heads on the one spike. Each additional head will add an Achaean\nmonth\nuntil the pike resets.\nAn upright travelling trunk:                                  150 Credits\nArtefact power:\noutfit\n_expansion\n- Double your outfit capacity!\n- This dapper trunk can also be used to store your wearables and has a capacity of 100 items.\nA wyrmskin\npack\n:                                              100 Credits\n- This pack can\nhold\nmore items than a standard pack!\n- For sale in\nMoghedu\n, right next to the entrance, in a\nshop\n.\nAn ornately carved ivory\npipe\n:                                50 Credits\n- This pipe remains lit permanently.\n- For sale in Moghedu, right next to the entrance, in a shop.\nA long, elegant ebony pipe:                                   50 Credits\n- This pipe remains lit permanently.\n- For sale in Moghedu, right next to the entrance, in a shop.\nA polished marble pipe:                                       50 Credits\n- This pipe remains lit permanently.\n- For sale in Moghedu, right next to the entrance, in a shop.\nA\nquartz\ncrystal\nvial\n:                                        40 Credits\n- This vial gives a 50% chance not to consume a sip of elixir or an\napplication\nof\nsalve\nor\nvenom\n.\n- For sale in Moghedu, right next to the entrance, in a shop.\n- Available in\ndiamond\n, ruby, sapphire, emerald, glass, quartz, amethyst, peridot, onyx, garnet, moonstone, and jade.\nA luxurious black top hat:                                    25 Credits\n- Luck of the\ndraw\n, indeed!\n- This beautiful top hat has various interesting properties.\n- It is a\ncontainer\n, and it holds 75 items: put what you want into it.\n- When you\nlook\nin it, all you see is if it's empty or not.\n- When you try to take\nanything\nout (GET\nx\nFROM HAT) you will not know in advance what item you are getting. The hat does not create new (or destroy existing) things, nor does it change the things you put in.\n- If you put in ten things, and pull out ten things, you'll still have the same ten things exactly. You just won't know what order they'll come out.\nTHINK\nOF THE POSSIBILITIES!\nA gilded coinbox:                                             900 Credits\nArtefact power:\nbanking\n- Portable access to all your\nbankaccounts\n.\n- This artefact does not exempt you from\nbank\nfees.\n- You may specify which bank to use with\nDEPOSIT\n<amt>\nGOLD\nIN <bank>.\nA Tinkerer's kit:                                             800 Credits\nArtefact power: tinkering\n- Use the REPAIR/ENGRAVE/EMBROIDER\ncommands\nwithout knowledge of the respective\ntradeskills\n.\n- Associated gold costs remain.\nAn Explorer's Tome:                                           500 Credits\n- This tome will allow you to see how much of an area you have explored.\n-\nSyntax\nfor use: READ <tome>.\nA shopper's guidebook:                                        350 Credits\nArtefact power: directory\n- Use the directory\ncommand\nfrom anywhere, for anywhere!\n- DIRECTORY <city> <item to find>\nA cask of Ironbeard's Finest:                                 150 Credits\n- This cask will make you considerably more\ndrunk\neach time you take a swig from it.\nA focusing lens:                                              150 Credits\nArtefact power: lastlogin\n- Use LASTLOGIN <playername> on your mutual\nallies\nto see when they last logged in to\nAchaea\n!\nA\nphial\nof shimmering permanent\nink\n:                          100 Credits\n- Make an existing\ntattoo\npermanent.\n- TRACE OVER <existing tattoo> ON <body part> WITH PERMANENT INK.\n- See\nHELP ARTEFACTTATTOOS\nA pair of ivory\ndice\n:                                         50 Credits\n- Great at\nparties\n!\n- ROLLDICE will allow you to roll the pair of dice, allowing you to\nrun\ngambling\nrings, etc.\n- ROLLDICE <count> <sides> will allow you to roll up to 10 dice with anywhere from 4 to 100 sides each.\nA\ntaper\nof eternity:                                          50 Credits\n- Provides an endless supply of sealing wax, as well as granting access to several exclusive colours.\n- See HELP 7.\n19\nfor the colours available.\nA signet ring:                                                50 Credits\n- Allows you to sign\nletters\nwith your personal coat of arms. (You have to have a coat of arms already.)\n- SEAL <letter> WITH <ring>\n- SIGN <letter> WITH <ring>\nA painter's palette:                                          450 Credits\n- Generates\ninks\nevery Achaean month.\nA horn of plenty:                                             250 Credits\n- This horn will periodically\nfill\nwith various\nfood\n.\n- The horn will regularly produce up to six different kinds of food, including a turkey potpie,\nwaybread\n, a smoked wheel of cheddar, and more.\n- If you purchase a horn of plenty, you can also\nemail\ncustomisations\n@achaea.com regarding\ncustomising\nwhat sort of food it produces, at additional per-item\ncredit\ncost of minimum 100 credits per item.\nAn enormous vat shaped as a dragon's head:                    250 Credits\n- This vat will\nrefill\nwith dragon's tears.\n- 10 applications of the combustible substance will refill into the vat every Achaean\nday\n, up to a maximum of 50.\nA satin-wrapped box of chocolates:                            200 Credits\n- This box generates chocolates.\n-\n18\ntypes of chocolates are available, and sometimes more are added!\nA clay flowerpot:                                             200 Credits\n- This flower pot will generate flowers every Achaean month.\n- 33% chance of growing one random flower (out of 17 types) every Achaean day. The flowerpot holds\n6\nflowers, and will stop producing them when full, until you pick one.\nA\ndrinking\nhorn:                                              150 Credits\n- This horn will periodically fill with ale.\n- For additional credits (50-250+ depending on type of liquor), you can customise what kind of liquor is produced in the\nflagon\nevery Achaean day. For example, if you want the horn to replenish with beer or\nmead\ninstead of ale, you can request this\ncustomisation\non your horn for 50 credits. You can request non-alcoholic liquids as well, such as apple juice or\ntea\n. Some liquids are not available, such as fairy nectar. You can also add more draughts per Achaean month for additional credits.\n- For exact price\nquotes\nand availability, please email customisations@achaea.com.\nA decorative brass cigar box:                                 100 Credits\n- This box will periodically fill with up to 5 cigars.\n- The box will produce one cigar per Achaean day and hold up to five at a time.\nA wyvernskin tabac pouch with a brass clasp:                  100 Credits\n- This pouch will periodically fill with tabac.\n- The pouch will produce one tabac per Achaean day and hold up to eight at a time.\nA collar of\nLupus\n:                                            250 Credits\n- Attach this to your\nmount\nto make it reset to you.\n- ATTACH <collar> TO <mount> that is loyal to you, excluding chimeras and inflatable giraffes, but including falcons and snakes. Makes the mount reset to you approximately every 18\nhours\n. Can never be killed permanently. *NEW: May be used with some customised\nclass\nloyals (see\nHELP CUSTOMISATION\nfor more details).\n********************************************************************\n* NOTE: this particular artefact cannot be traded in at all.       *\n* NOTE: this artefact may be used exactly once and no longer       *\n* exists after it is used. It may not be removed or transferred,   *\n* nor may the now-resetting-to-you mount be traded or transferred  *\n* NOTE: This collar does not allow you to keep class loyals (such  *\n* as falcons and snakes) when\nquitting\nclass. If, through some     *\n* error, your class loyal stays with you after quitting class,     *\n* please report this at once. The cost of the Collar will not be   *\n* refunded, nor will a new Collar be issued, so be careful!        *\n********************************************************************\nA silver whistle:                                             500 Credits\n- Allows you to REQUEST LETTERs and\nPOST\nmail\nfrom anywhere.\n- Additionally, this item may be upgraded with a customised mail delivery\nmessage\nfor an additional fee. Email customisations@achaea.com for further information.\nA lavishly gilded\npet\ncage:                                   100 Credits\n- Display your\npets\n!\n- DROP <cage> in any room and it will reset there. (Owner only)\n- PUSH <cage> to be able to pick it up. The cage will then reset to the owner's inventory once more. (Owner only)\n- The owner can TURN <cage> FOR <petID> and the pet will reset in the cage.\n- The owner can GET <pet> FROM <cage> and the pet will reset to their inventory again.\n- ANY player can take the pet from the cage, but it will reset back to the cage after an\nhour\n.\nA leadrope inlaid with silver:                                450 Credits\n- This leadrope will make it so that you do not\nlose\nyour loyal\ndenizen\nentourage\nwhen leaping or\ntumbling\n.\nA cage-bound parrot:                                          400 Credits\n- A master of mimicry, these birds will memorise any conversation they're privy to (up to an Achaean day in length.)\n- Being a somewhat small-brained creature, the parrot can only retain their memory of a conversation for\n2\nAchaean months.\n-\nTELL\n<parrot> TAKE NOTE - Start the Parrot's memorisation.\n- TELL <parrot> THAT'S ALL - Cease memorising a conversation.\n- TELL <parrot> REPEAT WHAT WAS SAID - Recite a conversation.\n- TELL <parrot> FASTER - Increase the\nspeed\nof a recitation.\n- TELL <parrot> SLOWER - Decrease the speed of a recitation.\n- TELL <parrot> FORGET - Forget the memorised conversation.\nProsperian Attractor:                                         200 Credits\nArtefact power: gold_attractor\n- Gold dropped from a denizen that you have killed goes directly to your inventory.\nA bag of\nsharing\n:                                             800 Credits\n- A pair of bags with a shared storage space.\n- Buy one with a\nfriend\nand easily pass anything from cakes to\nweapons\nto each\nother\n. Hold up to five items.\n- To purchase this bag, visit the Miscellaneous Artefact Shop in Delos with your intended partner and BUY <bag> PAIRED WITH <person>.\n- Like with Earrings of Sinope, the bag has one owner,\nwho\ncan change the partner at any time for a 150 credit fee.\nA mechanical box:                                             25 Credits\n- Try your luck with this nifty device for a chance to\nwin\ntalisman\npieces\nvia SPIN DIAL <boxID>.\n- If you match all three symbols you'll earn a talisman\npiece\nfrom the associated set (Wonders,\nDeath\n, or Blackwave).\n- If you only match two symbols, you'll get a quarter box (four quarter boxes = 1 whole box!).\n- If you match no symbols, you'll get a consolation prize.\nA supreme\ncollections\ncache:                                  50 Credits\n- A cache that you can OPEN for a random\nminipet\nfrom any\nCOLLECTION\n!\nAchaea is developed and published by\nIron Realms Entertainment.\nPrivacy Policy\nTerms Of Service\nSupport\nFollow us on Facebook!\nWe are using cookies to give you the best experience on our website.\nYou can find out more about which cookies we are using or switch them off in\nsettings\n.\nAccept\nScroll To Top\nClose GDPR Cookie Settings\nPrivacy Overview\nStrictly Necessary Cookies\nPrivacy Overview\nThis website uses cookies so that we can provide you with the best user experience possible. Cookie information is stored in your browser and performs functions such as recognising you when you return to our website and helping our team to understand which sections of the website you find most interesting and useful.\nStrictly Necessary Cookies\nStrictly Necessary Cookie should be enabled at all times so that we can save your preferences for cookie settings.\nEnable or Disable Cookies\nEnabled\nDisabled\nEnable All\nSave Changes"
}