{
  "page_id": "c7256384b85d4cc1-map-of-the-savannah",
  "url": "https://www.achaea.com/game-help/?what=map+of+the+savannah",
  "what": "map of the savannah",
  "title": "Game Help | Achaea",
  "section_number": null,
  "discovered_from": "topic-guess:8d5c30082dd7cf89-map-of-the-savannah",
  "command_candidates": [
    "HELP GAME HELP FILES FREQUENTLY ASKED QUESTIONS NEWBIE GUIDES HOW TO CONNECT EXTENSIONS SUPPORT CREDITS LOG IN ACHAEA HELP FILES ACHAEA HAS HUNDREDS OF HELP FILES TO YOU LEARN ABOUT ACHAEA. THIS IS A COPY OF THE IN-GAME HELP FILE STRUCTURE. HELP IN-GAME WILL SHOW YOU THIS SAME MENU. HELP",
    "HELP INDEX"
  ],
  "topic_candidates": [
    "; |",
    "______________________________________________________________________",
    "accept",
    "achaea maps",
    "achaea wiki",
    "aetolia",
    "aureliana",
    "city-states",
    "classes",
    "community",
    "credits",
    "dakhota",
    "desert",
    "disabled",
    "enable all",
    "enabled",
    "extensions",
    "features overview",
    "files",
    "files to you learn about achaea. this is a copy of the in-game help file structu",
    "forums",
    "frequently asked questions",
    "game",
    "game help files",
    "game help | achaea",
    "game logs",
    "game messages",
    "game news",
    "help:",
    "hills |",
    "history & mythos",
    "in-game will show you this same menu",
    "index",
    "iron realms entertainment",
    "iron realms entertainment!",
    "ithmia",
    "latest news",
    "log in",
    "lusternia",
    "mannaseh",
    "map of the savannah",
    "menu",
    "mhojave",
    "minia",
    "mountains d",
    "newbie guides",
    "play!",
    "portal",
    "privacy overview",
    "privacy policy",
    "races",
    "save changes",
    "scroll to top",
    "strictly necessary cookies",
    "support",
    "swamp |",
    "terms of service",
    "tomacula",
    "using the forums",
    "vashnar",
    "village |",
    "vundamere",
    "wilderness",
    "| i western",
    "| l lake",
    "| m"
  ],
  "text": "Game Help | Achaea\nSkip to content\nPlay more great MUDs from\nIron Realms Entertainment!\nAetolia\nLusternia\nMenu\nPlay!\nGame\nFeatures Overview\nCity-States\nClasses\nRaces\nThe Gods of Achaea\nHistory & Mythos\nAchaea Maps\nPortal\nGame Messages\nGame News\nGame Logs\nCommunity\nForums\nUsing The Forums\nJoin us on Discord!\nAchaea Wiki\nLatest News\nHelp\nGame Help Files\nFrequently Asked Questions\nNewbie Guides\nHow to Connect\nExtensions\nSupport\nCredits\nLog In\nAchaea Help Files\nAchaea has hundreds of help files to you learn about Achaea. This is a copy of the in-game help file structure. HELP in-game will show you this same menu.\nHelp:\n[\nReturn to Help Index\n]\n12.16.8 Map of the Savannah\n______________________________________________________________________\n| 1. Archway to\nMinia\n3\n.\nMannaseh\nSwamp                     |\n|\n2\n.\nTomacula\nVillage                                                  |\n|                                                                      |\n| - E-W   / NE-SW   > Up-Down\nX\nNE-SW, NW-SE   % Water               |\n|                                                                      |\n| | N-S   \\ NW-SE   ^ In-Out    + N-S, E-W       W\nWilderness\nentrance |\n|                                                                      |\n| M\nVashnar\nMountains     D\nMhojave\nDesert\nH\nDakhota\nHills         |\n| I Western\nIthmia\nA\nAureliana\nforest   B Black forest          |\n| L Lake\nVundamere\nR Road               T The great rock        |\n|                                                                      |\n| NOTES: IF two rooms are touching, they are -not- connected by\nexits\n; |\n|        The river may sweep you downstream, without your knowledge.   |\n|______________________________________________________________________|\n````````````````````````````````````````````````````````````````````````\n`````````````````````````````````````````````````````1``````````````````\n`````````````````````````````````````````````````````|``````````````````\n````````````````````````````````````````````````````-R````````````I`````\n`````````````````````````````````````````````````````|\\``````````/``````\n`````````````````````````````````````````````````````|`R-R------R```````\n`````````````````````````````````````````````````````|`|```````/`\\``````\n`````````````````````````````````````````````````````|`|``````/```\\`````\n```````````````````````````````````````````````````#^#-#`````/`````R```I\n````````````````````````````````````````````````````/``|\\```/```````\\`/`\n```````````````````````````````````````````````````/```L`\\`/`````````R``\n``````````````````````````````````````````````````/```````#`````````/|``\n```````````````````````````````````````````````A-#`````````\\```````/`|``\n`````````````````````````````````````````````````|``````````#-----#``|`I\n`````````````````````````````````````````````````|`````````/``````|``|/`\n```````````````````````````````````````````````A-#````````#```````#--R``\n`````````````````````````````````````````````````|````````|``````/````\\`\n`````````````````````````````````````````````````|``````L-#-----#```````\n```````````````````````````````````````````````A-#-L``````|````/````````\n```````B``````````````````````````````````````````\\`````L`|```/`````````\n````````\\``````````````````````````````````````````#````|`|```|`````````\n```````B`#-%```````````````````````````````````````|\\```#`|```|`````````\n```````|`|`````````````````````````````````````````|`\\`/`\\|```|`````````\n```````#-#-%```````````````````````````````````````#``#---#```|`````````\n```````|``\\````````````````````````````````````````|`#````````|`````````\n```````|```\\```````````````````````````````````````|``\\```````|`````````\n```````|````\\```````````````````A``````````````````#```#``````|`````````\n```````|`````\\``````````````````|`````````````````/`\\`/```````#`````````\n```````|````#`\\`````````````````#----------------#```#--#````/``````````\n```````|`````\\`\\````````````````|```````````````````/|`/|```/```````````\nR-#--#`|`#----#-#```````````````|``````````````````#`|#-#-#/````````````\n``|```\\|/````/``|```````````````#`````````````#````|`|````/`````````````\nR-#---T#````#```|```````````````|\\````````````|````#`|`#-#``````````````\n```\\`/`\\```/````|```````````````#`#-#`````````#``````|````\\`````````````\n````T```T-#`````|```````````````|````\\```````/`\\`````|```#-#````````````\n`````\\`/`/``````|```````````````#`````\\`````/```\\````|``/`\\`\\```````````\n``````T`#```````|``````````````/```````\\```/`````\\```#-#```#`\\``````````\n```````\\`\\``````|`````````````#`````````\\`/```````\\`/`/`\\``|``#`````````\n````````\\`#```#`|`````````````|\\`````````#-2```````#`#```\\`|`/``````````\n````````/``\\`/`\\|`````````````|`\\`````````\\````````|\\`````\\|#```````````\n````````\\```#```#-%```````````|``\\`````````\\```````W`\\`````#-#``````````\n`````````\\`/````|`````````````|```\\`````````\\`2````|``\\```/`/`\\`````````\n````````R-#`````|`````````````|````\\`````````\\|````2```\\`/`#```#````````\n``````````|`````|`````````````|`````\\`````````#---------#``|```|\\```````\n````````R`|`````|`````````````|``````\\```````/`\\````````|``|```|`M``````\n`````````\\|```%-%`````````````|```````#```#`#```#```````#--#---#-----#``\n``````````%```|`|\\````````````|```````|\\`/`````````````/```|``/`````/```\n``````````|```#`|`%-%`````````|`%-%-%`|`#`````````````/````|``|````/````\n``````````|````\\|````\\`````\\``|/```/`\\|`|````````````/`````|``|```#`````\n``````````R`````#`````%-%-%-%-%```#```%-%`3`````````/``````|``|``/``````\n```````````\\```/```````\\`````````/```````\\|````````/```````|``|``\\``````\n````````````R-#`````````#-------#`````````%-%-%```/````````|``|```\\`````\n````````````|```````````````````|``````````````\\`/`````````|``|````\\````\n````````````R```````````````````#```````````````%-----%----%``|`````\\```\n````````````|``````````````````>`\\`````#````````````````````\\`/`````/```\n````````````R`````````````````#```\\````|`````````````````````%`````/````\n`````````````\\```````````````>`````#```#``````````````````````\\```/`````\n``````````````R`````````````#`````/`\\`/|\\``````````````````````%-%-%````\n``````````````|``````````````````H```#-#-#-#````````````````````````\\```\n````````````M-R`````````````````````/```\\|/`````````````````````````````\n```````````````\\```````````````H-#-#`````#---#``````````````````````````\n``````````````M-R````````````````````````|``/```````````````````````````\n`````````````````\\```````````````````````#`#````````````````````````````\n``````````````````R`````````````````````/``|````````````````````````````\n```````````````````\\```````````````````D```#````````````````````````````\n````````````````````D`````````````````````/`````````````````````````````\n`````````````````````````````````````````D``````````````````````````````\n````````````````````````````````````````````````````````````````````````\n````````````````````````````````````````````````````````````````````````\nAchaea is developed and published by\nIron Realms Entertainment.\nPrivacy Policy\nTerms Of Service\nSupport\nFollow us on Facebook!\nWe are using cookies to give you the best experience on our website.\nYou can find out more about which cookies we are using or switch them off in\nsettings\n.\nAccept\nScroll To Top\nClose GDPR Cookie Settings\nPrivacy Overview\nStrictly Necessary Cookies\nPrivacy Overview\nThis website uses cookies so that we can provide you with the best user experience possible. Cookie information is stored in your browser and performs functions such as recognising you when you return to our website and helping our team to understand which sections of the website you find most interesting and useful.\nStrictly Necessary Cookies\nStrictly Necessary Cookie should be enabled at all times so that we can save your preferences for cookie settings.\nEnable or Disable Cookies\nEnabled\nDisabled\nEnable All\nSave Changes"
}