{
  "page_id": "f03c528273e5106e-game-help-achaea",
  "url": "https://www.achaea.com/game-help/?id=240",
  "what": null,
  "title": "Game Help | Achaea",
  "section_number": null,
  "discovered_from": "page-link:85159649a86b5fa6-building",
  "command_candidates": [
    "HELP DEVELOPMENT",
    "HELP GAME HELP FILES FREQUENTLY ASKED QUESTIONS NEWBIE GUIDES HOW TO CONNECT EXTENSIONS SUPPORT CREDITS LOG IN ACHAEA HELP FILES ACHAEA HAS HUNDREDS OF HELP FILES TO YOU LEARN ABOUT ACHAEA. THIS IS A COPY OF THE IN-GAME HELP FILE STRUCTURE. HELP IN-GAME WILL SHOW YOU THIS SAME MENU. HELP",
    "HELP HOUSING SUMMARY FOR AN OVERVIEW",
    "HELP HOUSING UPGRADES",
    "HELP INDEX",
    "HELP PERMISSIONS",
    "HELP PERMISSIONS FOR MORE INFORMATION ON PERMISSIONS.",
    "ROOM",
    "WHO CAN OPEN THE DOOR.",
    "WHO THE SELLER IS. IF IT IS UNOWNED"
  ],
  "topic_candidates": [
    "- see",
    "-------------",
    "--------------",
    "-----------------------",
    "-------------------------",
    "--------------------------------",
    "-------------------------------------",
    "------------------------------------------",
    "accept",
    "achaea maps",
    "achaea wiki",
    "aetolia",
    "and development",
    "building",
    "building a house",
    "cities",
    "city-states",
    "classes",
    "community",
    "credits",
    "delos",
    "development",
    "disabled",
    "divine",
    "enable all",
    "enabled",
    "everything",
    "extensions",
    "features overview",
    "files",
    "files to you learn about achaea. this is a copy of the in-game help file structu",
    "forums",
    "frequently asked questions",
    "game",
    "game help files",
    "game help | achaea",
    "game logs",
    "game messages",
    "game news",
    "help:",
    "history & mythos",
    "houses",
    "housing summary for an overview",
    "housing upgrades",
    "in-game will show you this same menu",
    "index",
    "iron realms entertainment",
    "iron realms entertainment!",
    "latest news",
    "log in",
    "look",
    "lusternia",
    "menu",
    "newbie guides",
    "orders",
    "permissions",
    "play!",
    "plots",
    "portal",
    "privacy overview",
    "privacy policy",
    "property office - individuals",
    "races",
    "room credit to buy a door",
    "save changes",
    "scroll to top",
    "ships' cabins",
    "shows",
    "strictly necessary cookies",
    "support",
    "terms of service",
    "using the forums"
  ],
  "text": "Game Help | Achaea\nSkip to content\nPlay more great MUDs from\nIron Realms Entertainment!\nAetolia\nLusternia\nMenu\nPlay!\nGame\nFeatures Overview\nCity-States\nClasses\nRaces\nThe Gods of Achaea\nHistory & Mythos\nAchaea Maps\nPortal\nGame Messages\nGame News\nGame Logs\nCommunity\nForums\nUsing The Forums\nJoin us on Discord!\nAchaea Wiki\nLatest News\nHelp\nGame Help Files\nFrequently Asked Questions\nNewbie Guides\nHow to Connect\nExtensions\nSupport\nCredits\nLog In\nAchaea Help Files\nAchaea has hundreds of help files to you learn about Achaea. This is a copy of the in-game help file structure. HELP in-game will show you this same menu.\nHelp:\n[\nReturn to Help Index\n]\n20.3 Building a House\n(See also: HELP HOUSING SUMMARY for an overview,\nHELP HOUSING UPGRADES\n,\nHELP PERMISSIONS\n, and\nHELP\nDEVELOPMENT)\nHouses\nand Rooms: No Sale or Transfer\n-------------------------------------\nHouses may not be sold, transferred, or traded in, although the individual\nrooms may be destroyed and some value may be recaptured in that way.\nDestroying the rooms and\ndoors\nof a\nhouse\nreturns approximately half\ncredit\n.\nPlots\nmay not be sold if they have houses on them.\nIn the\nDelos\nProperty Office - Individuals\n------------------------------------------\nBUY\nROOM - 200\nwood\nand 100 stone\ncomms\n.\n- Purchases a single room credit. It takes 10 room\ncredits\nto buy a room.\nIt also takes but a single room credit to buy a door for your house.\nBUY ROOM AS GIFT FOR <person>\n- Purchase a room credit for someone else.\nLook\nat you! So nice.\nIn the Delos Property Office - Organisations (Houses,\nCities\n, and\nOrders\n)\n-------------------------------------------------------------------------\nOrg-owned houses may be created only in\nship\ncabins\nat this\ntime\n.\nBUY ROOM FOR <org> - 200 wood, 100 stone comms.\n- Purchases a room credit. It takes 10 room credits to build a new room and\n1 room credit to buy a door.\n- Orgs may possess no more than 5000 room credits at any one time.\nWhile anywhere\n--------------\nPLOTS OWNED\n-\nShows\nyou a list of plots you own.\nWhile in a\nsubdivision\nin a\ncity\n--------------------------------\nPLOTS\n- Shows you a list of all plots for sale in that subdivision. It provides\nthe coordinates for a\nplot\n, the price, and the seller. Note that if the\nseller is listed merely as '-' then the seller is the city that owns the\nsubdivision.\nPLOT INFO\n- Shows you how much the plot is\ngoing\nfor, and\nwho\nthe seller is. If it is\nunowned, it means it is a virgin plot, being sold by the city.\nPLOT BUY\n- Purchase the plot for yourself.\n- The price is variable, depending on what the city has set it as.\nPLOT PRICE <price in gold>\n- PLOT PRICE (1 to 1 billion\ngold\n) to offer your plot for sale.\n- PLOT PRICE 0 to no longer offer your plot for sale.\n- Must be standing on the plot.\nPLOT TRANSFER <person>\n- Transfers ownership of your plot to someone else.\n- Must be standing on the plot.\nHOUSING\nCREATE\n- Creates a house from your location, leading 'in'. The house will have\none room, and will be owned by you.\n- You must have 10 room credits to do this.\n- You will be told what the number of your house is.\n- An 'in'\nexit\nwill be created to the first room of your house. That exit\nmay not be destroyed.\n- While your house is owned by you, the subdivision is under the\njurisdiction of the city it is in. Be aware that the city may regulate\naccess to the subdivision, and therefore, your house.\n- Org-owned houses may be created only in ship cabins at this time.\nHOUSING CREATE FOR org\n- Creates a house from your location, leading 'in'. The house will have\none room, and will be owned by the org, of which you must be the\nDivine\nPatron or the mortal leader or Order head.\n- It costs 10 room credits to do this.\n- You will be told what the number of the house is.\n- An 'in' exit will be created to the first room of the house. That exit\nmay not be destroyed.\n- Org-owned houses may be created only in ship cabins at this time, with the\nexception of\nclan\nhousing.\nOut of Subdivision Houses\n-------------------------\nBuilding\ncosts related to housing (rooms and doors) in out of subdivision\nhouses cost twice as much, per room as in-subdivision houses. Upgrades cost\nthe same as in subdivision houses.\nShips' Cabins\n-------------\nAll costs related to housing (rooms, upgrades, etc) in ships' cabins are\ndoubled, this is per room or upgrade.\nThe limit to the number of rooms that may be added in a ship's\ncabin\n, relates\nto the size of the ship, 1 to 1. So a ship of size\n2\n, such as a Windcutter,\ncan have a 2-room cabin expansion. A ship of size\n5\n, such as a Seastrider,\ncan have a 5-room cabin expansion.\nManipulating your house\n-----------------------\nHOUSING LIST\n- Lists your houses, as well as how many room credits you have.\nHOUSING CREATE ROOM <direction>\n- Creates a room in the house you're standing in, to the\ndirection\nyou\nspecify.\n- Costs 10 room credits.\nHOUSING ROOM LIST <house #>\n- Lists the rooms in a house.\nHOUSING SET HOUSE\nTITLE\n<title>\n- Sets the title of the house you're standing in.\n- Costs 10,000 gold.\n- Limit of 55 characters.\nHOUSING SET ROOM TITLE <title>\n- Sets room title for room you are in.\n- Costs 10,000 gold.\n- Limit of 55 characters.\n- You may not set room\ntitles\nthat make it appear as if you are somewhere\nyou are not, such as \"North of New Thera\". There will be\npenalties\nif\nyou do.\nHOUSING EDIT ROOM DESC/\nDESCRIPTION\n- Sends you into\neditor\nto edit the description of this room.\n- Costs 10,000 gold.\nHOUSING DESTROY ROOM <direction>\n- Destroys a room to the <direction>.\n- You will get 5 room credits in return.\n- You cannot destroy a room such that any\nother\nrooms would be cut\noff from the rest of the\nworld\n.\n- You cannot destroy a room that has any doors in it.\n-\nEverything\nin a room that you destroy will be destroyed along with the\nroom.\n- IF YOU HAVE FURNITURE in the room, it will be destroyed too.\nSo if you want to relocate furniture, do it BEFORE you destroy it!\nHOUSING CREATE EXIT <direction> <other room in house>\n- Create an exit within a house.\n- Costs 1,000 gold.\n- Use HOUSING ROOM LIST <house> to see a list of rooms in that house.\nHOUSING DESTROY EXIT <direction>\n- Destroys an exit. It will not let you strand rooms such that they're\ncut off from the rest of the world.\n- No cost.\nHOUSING HIDE EXIT <direction>\n- Hides an exit. The SECRETS\ncommand\nwill give a chance of seeing it.\n- Costs 50,000 gold.\n- When an exit is destroyed, no refund is given, so do not use this\nwilly-nilly.\nHOUSING REVEAL EXIT <direction>\n- Reveals an exit.\n- Reveals a previously hidden exit.\n- This does not give one a refund of the hide price.\nHOUSING CREATE DOOR <direction>\n- Creates a door.\n- Requires one room credit.\nHOUSING DESTROY DOOR <direction>\n- Destroys a door.\n- This gives you back one room credit.\nHOUSING SET DOOR\nPERMS\n/\nPERMISSIONS\n<dir> <permission>\n- Sets permissions on who can open the door.\n- If no permissions are set, anyone will be able to open the door.\n- See\nHELP PERMISSIONS\nfor more information on permissions.\n- No cost.\nHOUSING LIST DOOR PERMS/PERMISSIONS <dir>\n- List the permissions on a door.\nHOUSING\nREMOVE\nDOOR PERMS/PERMISSIONS <dir> <\npermission\nstring>\n- Removes a specific door permission.\nHOUSING CLEAR DOOR PERMS/PERMISSIONS <dir>\n- Clears a door's permissions.\n(See also: HELP HOUSING SUMMARY for an overview,\nHELP HOUSING UPGRADES\n,\nHELP PERMISSIONS\n, and HELP DEVELOPMENT)\nAchaea is developed and published by\nIron Realms Entertainment.\nPrivacy Policy\nTerms Of Service\nSupport\nFollow us on Facebook!\nWe are using cookies to give you the best experience on our website.\nYou can find out more about which cookies we are using or switch them off in\nsettings\n.\nAccept\nScroll To Top\nClose GDPR Cookie Settings\nPrivacy Overview\nStrictly Necessary Cookies\nPrivacy Overview\nThis website uses cookies so that we can provide you with the best user experience possible. Cookie information is stored in your browser and performs functions such as recognising you when you return to our website and helping our team to understand which sections of the website you find most interesting and useful.\nStrictly Necessary Cookies\nStrictly Necessary Cookie should be enabled at all times so that we can save your preferences for cookie settings.\nEnable or Disable Cookies\nEnabled\nDisabled\nEnable All\nSave Changes"
}